{
  "url": "https://www.chanceliga.cz/zapas/8057-boh-sks",
  "meta": {
    "home_team": "Bohemians Praha 1905",
    "away_team": "SK Slavia Praha",
    "home_score": 0,
    "away_score": 2,
    "home_score_ht": 0,
    "away_score_ht": 1,
    "round": "2. kolo, Základní část | sobota 26/07/2025, 20:00 | Ďolíček |",
    "date": "26/07/2025 20:00",
    "stadium": "Ďolíček",
    "referee": "O. Pechanec"
  },
  "events": [
    {
      "type": "goal",
      "team": "away",
      "player": "Lukáš Provod",
      "minute": 39
    },
    {
      "type": "goal",
      "team": "away",
      "player": "Vasil Kušej",
      "minute": 70
    },
    {
      "type": "yellow_card",
      "team": "home",
      "player": "Benson Sakala",
      "minute": 75
    },
    {
      "type": "yellow_card",
      "team": "home",
      "player": "Robert Hrubý",
      "minute": 86
    },
    {
      "type": "yellow_card",
      "team": "away",
      "player": "Christos Zafeiris",
      "minute": 45
    },
    {
      "type": "yellow_card",
      "team": "away",
      "player": "Tomáš Chorý",
      "minute": 68
    },
    {
      "type": "yellow_card",
      "team": "away",
      "player": "David Zima",
      "minute": 79
    },
    {
      "type": "yellow_card",
      "team": "away",
      "player": "David Moses",
      "minute": 90
    }
  ],
  "stats": {
    "total": {
      "possession": {
        "home": 39,
        "away": 61
      },
      "shots": {
        "home": 5,
        "away": 14
      },
      "shots_on_target": {
        "home": 1,
        "away": 6
      },
      "corners": {
        "home": 3,
        "away": 11
      },
      "passes": {
        "home": 112,
        "away": 218
      },
      "pass_accuracy": {
        "home": 54.9,
        "away": 69.9
      },
      "duels_won": {
        "home": 54,
        "away": 56
      },
      "fouls": {
        "home": 15,
        "away": 17
      },
      "xg": {
        "home": 1.13,
        "away": 1.05
      },
      "offsides": {
        "home": 2,
        "away": 4
      },
      "yellow_cards": {
        "home": 2,
        "away": 4
      }
    }
  },
  "lineups": {
    "home": [
      {
        "name": "12",
        "number": null,
        "position": "B",
        "starter": true,
        "goals": 0,
        "yellow_cards": 0,
        "red_cards": 0
      },
      {
        "name": "28",
        "number": null,
        "position": "O",
        "starter": true,
        "goals": 0,
        "yellow_cards": 0,
        "red_cards": 0
      },
      {
        "name": "22",
        "number": null,
        "position": "O",
        "starter": true,
        "goals": 0,
        "yellow_cards": 0,
        "red_cards": 0
      },
      {
        "name": "7",
        "number": null,
        "position": "O",
        "starter": true,
        "goals": 0,
        "yellow_cards": 0,
        "red_cards": 0
      },
      {
        "name": "99",
        "number": null,
        "position": "O",
        "starter": true,
        "goals": 0,
        "yellow_cards": 0,
        "red_cards": 0
      },
      {
        "name": "27",
        "number": null,
        "position": "O",
        "starter": true,
        "goals": 0,
        "yellow_cards": 0,
        "red_cards": 0
      },
      {
        "name": "41",
        "number": null,
        "position": "Z",
        "starter": true,
        "goals": 0,
        "yellow_cards": 0,
        "red_cards": 0
      },
      {
        "name": "6",
        "number": null,
        "position": "Z",
        "starter": true,
        "goals": 0,
        "yellow_cards": 1,
        "red_cards": 0
      },
      {
        "name": "9",
        "number": null,
        "position": "U",
        "starter": true,
        "goals": 0,
        "yellow_cards": 0,
        "red_cards": 0
      },
      {
        "name": "20",
        "number": null,
        "position": "U",
        "starter": true,
        "goals": 0,
        "yellow_cards": 0,
        "red_cards": 0
      },
      {
        "name": "77",
        "number": null,
        "position": "U",
        "starter": true,
        "goals": 0,
        "yellow_cards": 0,
        "red_cards": 0
      },
      {
        "name": "25",
        "number": null,
        "position": "O",
        "starter": false,
        "goals": 0,
        "yellow_cards": 0,
        "red_cards": 0
      },
      {
        "name": "18",
        "number": null,
        "position": "O",
        "starter": false,
        "goals": 0,
        "yellow_cards": 0,
        "red_cards": 0
      },
      {
        "name": "70",
        "number": null,
        "position": "Z",
        "starter": false,
        "goals": 0,
        "yellow_cards": 0,
        "red_cards": 0
      },
      {
        "name": "8",
        "number": null,
        "position": "Z",
        "starter": false,
        "goals": 0,
        "yellow_cards": 1,
        "red_cards": 0
      },
      {
        "name": "23",
        "number": null,
        "position": "B",
        "starter": false,
        "goals": 0,
        "yellow_cards": 0,
        "red_cards": 0
      },
      {
        "name": "71",
        "number": null,
        "position": "B",
        "starter": false,
        "goals": 0,
        "yellow_cards": 0,
        "red_cards": 0
      },
      {
        "name": "35",
        "number": null,
        "position": "O",
        "starter": false,
        "goals": 0,
        "yellow_cards": 0,
        "red_cards": 0
      },
      {
        "name": "66",
        "number": null,
        "position": "Z",
        "starter": false,
        "goals": 0,
        "yellow_cards": 0,
        "red_cards": 0
      }
    ],
    "away": [
      {
        "name": "36",
        "number": null,
        "position": "B",
        "starter": true,
        "goals": 0,
        "yellow_cards": 0,
        "red_cards": 0
      },
      {
        "name": "4",
        "number": null,
        "position": "O",
        "starter": true,
        "goals": 0,
        "yellow_cards": 1,
        "red_cards": 0
      },
      {
        "name": "18",
        "number": null,
        "position": "O",
        "starter": true,
        "goals": 0,
        "yellow_cards": 0,
        "red_cards": 0
      },
      {
        "name": "33",
        "number": null,
        "position": "O",
        "starter": true,
        "goals": 0,
        "yellow_cards": 0,
        "red_cards": 0
      },
      {
        "name": "3",
        "number": null,
        "position": "O",
        "starter": true,
        "goals": 0,
        "yellow_cards": 0,
        "red_cards": 0
      },
      {
        "name": "23",
        "number": null,
        "position": "Z",
        "starter": true,
        "goals": 0,
        "yellow_cards": 0,
        "red_cards": 0
      },
      {
        "name": "17",
        "number": null,
        "position": "Z",
        "starter": true,
        "goals": 1,
        "yellow_cards": 0,
        "red_cards": 0
      },
      {
        "name": "21",
        "number": null,
        "position": "Z",
        "starter": true,
        "goals": 0,
        "yellow_cards": 0,
        "red_cards": 0
      },
      {
        "name": "10",
        "number": null,
        "position": "Z",
        "starter": true,
        "goals": 0,
        "yellow_cards": 1,
        "red_cards": 0
      },
      {
        "name": "9",
        "number": null,
        "position": "U",
        "starter": true,
        "goals": 1,
        "yellow_cards": 0,
        "red_cards": 0
      },
      {
        "name": "25",
        "number": null,
        "position": "U",
        "starter": true,
        "goals": 0,
        "yellow_cards": 1,
        "red_cards": 0
      },
      {
        "name": "2",
        "number": null,
        "position": "O",
        "starter": false,
        "goals": 0,
        "yellow_cards": 0,
        "red_cards": 0
      },
      {
        "name": "8",
        "number": null,
        "position": "O",
        "starter": false,
        "goals": 0,
        "yellow_cards": 0,
        "red_cards": 0
      },
      {
        "name": "16",
        "number": null,
        "position": "Z",
        "starter": false,
        "goals": 0,
        "yellow_cards": 1,
        "red_cards": 0
      },
      {
        "name": "19",
        "number": null,
        "position": "Z",
        "starter": false,
        "goals": 0,
        "yellow_cards": 0,
        "red_cards": 0
      },
      {
        "name": "13",
        "number": null,
        "position": "U",
        "starter": false,
        "goals": 0,
        "yellow_cards": 0,
        "red_cards": 0
      },
      {
        "name": "35",
        "number": null,
        "position": "B",
        "starter": false,
        "goals": 0,
        "yellow_cards": 0,
        "red_cards": 0
      },
      {
        "name": "15",
        "number": null,
        "position": "O",
        "starter": false,
        "goals": 0,
        "yellow_cards": 0,
        "red_cards": 0
      },
      {
        "name": "20",
        "number": null,
        "position": "Z",
        "starter": false,
        "goals": 0,
        "yellow_cards": 0,
        "red_cards": 0
      },
      {
        "name": "29",
        "number": null,
        "position": "Z",
        "starter": false,
        "goals": 0,
        "yellow_cards": 0,
        "red_cards": 0
      },
      {
        "name": "11",
        "number": null,
        "position": "Z",
        "starter": false,
        "goals": 0,
        "yellow_cards": 0,
        "red_cards": 0
      },
      {
        "name": "26",
        "number": null,
        "position": "U",
        "starter": false,
        "goals": 0,
        "yellow_cards": 0,
        "red_cards": 0
      }
    ]
  },
  "match_id": 8057
}