{
  "url": "https://www.chanceliga.cz/zapas/8228-lib-hkr",
  "meta": {
    "home_team": "FC Slovan Liberec",
    "away_team": "FC Hradec Králové",
    "home_score": 0,
    "away_score": 1,
    "home_score_ht": 0,
    "away_score_ht": 1,
    "round": "24. kolo, Základní část | sobota 28/02/2026, 15:00 | Stadión U Nisy |",
    "date": "28/02/2026 15:00",
    "stadium": "Stadión U Nisy",
    "referee": "O. Berka"
  },
  "events": [
    {
      "type": "goal",
      "team": "away",
      "player": "Václav Pilař",
      "minute": 38
    },
    {
      "type": "yellow_card",
      "team": "home",
      "player": "Lukáš Letenay",
      "minute": 90
    },
    {
      "type": "yellow_card",
      "team": "home",
      "player": "Daniel Rus",
      "minute": 90
    },
    {
      "type": "yellow_card",
      "team": "away",
      "player": "Ondřej Mihálik",
      "minute": 90
    }
  ],
  "stats": {
    "total": {
      "possession": {
        "home": 55,
        "away": 45
      },
      "shots": {
        "home": 9,
        "away": 7
      },
      "shots_on_target": {
        "home": 2,
        "away": 3
      },
      "corners": {
        "home": 8,
        "away": 6
      },
      "passes": {
        "home": 309,
        "away": 245
      },
      "pass_accuracy": {
        "home": 74.5,
        "away": 72.9
      },
      "duels_won": {
        "home": 39,
        "away": 37
      },
      "fouls": {
        "home": 12,
        "away": 13
      },
      "xg": {
        "home": 0.42,
        "away": 0.33
      },
      "offsides": {
        "home": 2,
        "away": 3
      },
      "yellow_cards": {
        "home": 2,
        "away": 1
      }
    }
  },
  "lineups": {
    "home": [
      {
        "name": "40",
        "number": null,
        "position": "B",
        "starter": true,
        "goals": 0,
        "yellow_cards": 0,
        "red_cards": 0
      },
      {
        "name": "16",
        "number": null,
        "position": "O",
        "starter": true,
        "goals": 0,
        "yellow_cards": 0,
        "red_cards": 0
      },
      {
        "name": "27",
        "number": null,
        "position": "O",
        "starter": true,
        "goals": 0,
        "yellow_cards": 0,
        "red_cards": 0
      },
      {
        "name": "24",
        "number": null,
        "position": "Z",
        "starter": true,
        "goals": 0,
        "yellow_cards": 0,
        "red_cards": 0
      },
      {
        "name": "20",
        "number": null,
        "position": "Z",
        "starter": true,
        "goals": 0,
        "yellow_cards": 0,
        "red_cards": 0
      },
      {
        "name": "8",
        "number": null,
        "position": "Z",
        "starter": true,
        "goals": 0,
        "yellow_cards": 0,
        "red_cards": 0
      },
      {
        "name": "12",
        "number": null,
        "position": "Z",
        "starter": true,
        "goals": 0,
        "yellow_cards": 0,
        "red_cards": 0
      },
      {
        "name": "26",
        "number": null,
        "position": "Z",
        "starter": true,
        "goals": 0,
        "yellow_cards": 0,
        "red_cards": 0
      },
      {
        "name": "30",
        "number": null,
        "position": "Z",
        "starter": true,
        "goals": 0,
        "yellow_cards": 0,
        "red_cards": 0
      },
      {
        "name": "9",
        "number": null,
        "position": "U",
        "starter": true,
        "goals": 0,
        "yellow_cards": 0,
        "red_cards": 0
      },
      {
        "name": "99",
        "number": null,
        "position": "U",
        "starter": true,
        "goals": 0,
        "yellow_cards": 0,
        "red_cards": 0
      },
      {
        "name": "5",
        "number": null,
        "position": "O",
        "starter": false,
        "goals": 0,
        "yellow_cards": 0,
        "red_cards": 0
      },
      {
        "name": "15",
        "number": null,
        "position": "Z",
        "starter": false,
        "goals": 0,
        "yellow_cards": 0,
        "red_cards": 0
      },
      {
        "name": "7",
        "number": null,
        "position": "Z",
        "starter": false,
        "goals": 0,
        "yellow_cards": 0,
        "red_cards": 0
      },
      {
        "name": "21",
        "number": null,
        "position": "U",
        "starter": false,
        "goals": 0,
        "yellow_cards": 1,
        "red_cards": 0
      },
      {
        "name": "29",
        "number": null,
        "position": "U",
        "starter": false,
        "goals": 0,
        "yellow_cards": 1,
        "red_cards": 0
      },
      {
        "name": "1",
        "number": null,
        "position": "B",
        "starter": false,
        "goals": 0,
        "yellow_cards": 0,
        "red_cards": 0
      },
      {
        "name": "18",
        "number": null,
        "position": "O",
        "starter": false,
        "goals": 0,
        "yellow_cards": 0,
        "red_cards": 0
      },
      {
        "name": "3",
        "number": null,
        "position": "O",
        "starter": false,
        "goals": 0,
        "yellow_cards": 0,
        "red_cards": 0
      },
      {
        "name": "28",
        "number": null,
        "position": "Z",
        "starter": false,
        "goals": 0,
        "yellow_cards": 0,
        "red_cards": 0
      },
      {
        "name": "11",
        "number": null,
        "position": "U",
        "starter": false,
        "goals": 0,
        "yellow_cards": 0,
        "red_cards": 0
      },
      {
        "name": "17",
        "number": null,
        "position": "U",
        "starter": false,
        "goals": 0,
        "yellow_cards": 0,
        "red_cards": 0
      }
    ],
    "away": [
      {
        "name": "12",
        "number": null,
        "position": "B",
        "starter": true,
        "goals": 0,
        "yellow_cards": 0,
        "red_cards": 0
      },
      {
        "name": "7",
        "number": null,
        "position": "O",
        "starter": true,
        "goals": 0,
        "yellow_cards": 0,
        "red_cards": 0
      },
      {
        "name": "5",
        "number": null,
        "position": "O",
        "starter": true,
        "goals": 0,
        "yellow_cards": 0,
        "red_cards": 0
      },
      {
        "name": "25",
        "number": null,
        "position": "O",
        "starter": true,
        "goals": 0,
        "yellow_cards": 0,
        "red_cards": 0
      },
      {
        "name": "26",
        "number": null,
        "position": "O",
        "starter": true,
        "goals": 0,
        "yellow_cards": 0,
        "red_cards": 0
      },
      {
        "name": "28",
        "number": null,
        "position": "Z",
        "starter": true,
        "goals": 0,
        "yellow_cards": 0,
        "red_cards": 0
      },
      {
        "name": "6",
        "number": null,
        "position": "Z",
        "starter": true,
        "goals": 1,
        "yellow_cards": 0,
        "red_cards": 0
      },
      {
        "name": "16",
        "number": null,
        "position": "Z",
        "starter": true,
        "goals": 0,
        "yellow_cards": 0,
        "red_cards": 0
      },
      {
        "name": "27",
        "number": null,
        "position": "Z",
        "starter": true,
        "goals": 0,
        "yellow_cards": 0,
        "red_cards": 0
      },
      {
        "name": "58",
        "number": null,
        "position": "Z",
        "starter": true,
        "goals": 0,
        "yellow_cards": 0,
        "red_cards": 0
      },
      {
        "name": "17",
        "number": null,
        "position": "U",
        "starter": true,
        "goals": 0,
        "yellow_cards": 1,
        "red_cards": 0
      },
      {
        "name": "2",
        "number": null,
        "position": "O",
        "starter": false,
        "goals": 0,
        "yellow_cards": 0,
        "red_cards": 0
      },
      {
        "name": "23",
        "number": null,
        "position": "Z",
        "starter": false,
        "goals": 0,
        "yellow_cards": 0,
        "red_cards": 0
      },
      {
        "name": "77",
        "number": null,
        "position": "Z",
        "starter": false,
        "goals": 0,
        "yellow_cards": 0,
        "red_cards": 0
      },
      {
        "name": "19",
        "number": null,
        "position": "Z",
        "starter": false,
        "goals": 0,
        "yellow_cards": 0,
        "red_cards": 0
      },
      {
        "name": "18",
        "number": null,
        "position": "U",
        "starter": false,
        "goals": 0,
        "yellow_cards": 0,
        "red_cards": 0
      },
      {
        "name": "1",
        "number": null,
        "position": "B",
        "starter": false,
        "goals": 0,
        "yellow_cards": 0,
        "red_cards": 0
      },
      {
        "name": "20",
        "number": null,
        "position": "B",
        "starter": false,
        "goals": 0,
        "yellow_cards": 0,
        "red_cards": 0
      },
      {
        "name": "8",
        "number": null,
        "position": "O",
        "starter": false,
        "goals": 0,
        "yellow_cards": 0,
        "red_cards": 0
      },
      {
        "name": "14",
        "number": null,
        "position": "U",
        "starter": false,
        "goals": 0,
        "yellow_cards": 0,
        "red_cards": 0
      }
    ]
  },
  "match_id": 8228
}