{
  "slug": "saison-2025-2026-jupiler-pro-league-31-club-brugge-vs-rsc-anderlecht",
  "date": "2026-04-06",
  "round": 31,
  "round_name": "Journée 31",
  "status": "FullTime",
  "referee": "Jasper Vergoote",
  "attendance": null,
  "home_team": "Club Brugge",
  "away_team": "Royal Sporting Club Anderlecht",
  "home_score": 4,
  "away_score": 2,
  "home_formation": "4231",
  "away_formation": "4231",
  "home": {
    "shots": 30,
    "shots_on_target": 9,
    "shots_off_target": 8,
    "shots_blocked": 13,
    "corners": 8,
    "corners_taken": 8,
    "corners_conceded": 2,
    "fouls": 11,
    "fouls_won": 14,
    "yellow_cards": 2,
    "possession": 57.9,
    "passes": 517,
    "passes_accurate": 446,
    "tackles_won": 7,
    "tackles": 12,
    "saves": 4,
    "clearances": 13,
    "big_chances_missed": 1,
    "goals": 4,
    "assists": 4
  },
  "away": {
    "shots": 13,
    "shots_on_target": 6,
    "shots_off_target": 4,
    "shots_blocked": 3,
    "corners": 2,
    "corners_taken": 2,
    "corners_conceded": 8,
    "fouls": 14,
    "fouls_won": 8,
    "yellow_cards": 1,
    "possession": 42.1,
    "passes": 379,
    "passes_accurate": 298,
    "offsides": 1,
    "tackles_won": 10,
    "tackles": 12,
    "saves": 3,
    "clearances": 17,
    "goals": 2,
    "assists": 1
  }
}