{
  "slug": "saison-2025-2026-jupiler-pro-league-23-union-sg-vs-club-brugge",
  "date": "2026-02-01",
  "round": 23,
  "round_name": "Journée 23",
  "status": "FullTime",
  "referee": "Nathan Verboomen",
  "attendance": null,
  "home_team": "Royale Union St-Gilloise",
  "away_team": "Club Brugge",
  "home_score": 1,
  "away_score": 0,
  "home_formation": "3421",
  "away_formation": "433",
  "home": {
    "shots": 13,
    "shots_on_target": 5,
    "shots_off_target": 6,
    "shots_blocked": 2,
    "corners": 5,
    "corners_taken": 5,
    "corners_conceded": 5,
    "fouls": 12,
    "fouls_won": 11,
    "yellow_cards": 3,
    "possession": 30.1,
    "passes": 278,
    "passes_accurate": 206,
    "offsides": 1,
    "tackles_won": 9,
    "tackles": 14,
    "saves": 2,
    "clearances": 33,
    "big_chances_missed": 2,
    "goals": 1,
    "assists": 1
  },
  "away": {
    "shots": 8,
    "shots_on_target": 2,
    "shots_off_target": 3,
    "shots_blocked": 3,
    "corners": 5,
    "corners_taken": 5,
    "corners_conceded": 5,
    "fouls": 11,
    "fouls_won": 12,
    "yellow_cards": 3,
    "possession": 69.9,
    "passes": 642,
    "passes_accurate": 566,
    "tackles_won": 9,
    "tackles": 15,
    "saves": 4,
    "clearances": 23
  }
}