{
  "slug": "saison-2025-2026-jupiler-pro-league-10-kvc-westerlo-vs-oh-leuven",
  "date": "2025-10-05",
  "round": 10,
  "round_name": "Journée 10",
  "status": "FullTime",
  "referee": "Lothar D'Hondt",
  "attendance": null,
  "home_team": "KVC Westerlo",
  "away_team": "OH Leuven",
  "home_score": 2,
  "away_score": 0,
  "home_formation": "4231",
  "away_formation": "343",
  "home": {
    "shots": 17,
    "shots_on_target": 5,
    "shots_off_target": 7,
    "shots_blocked": 5,
    "corners": 6,
    "corners_taken": 6,
    "corners_conceded": 6,
    "fouls": 13,
    "fouls_won": 27,
    "yellow_cards": 2,
    "possession": 51.8,
    "passes": 351,
    "passes_accurate": 291,
    "offsides": 1,
    "tackles_won": 7,
    "tackles": 21,
    "saves": 4,
    "clearances": 56,
    "big_chances_missed": 2,
    "goals": 2,
    "assists": 2
  },
  "away": {
    "shots": 8,
    "shots_on_target": 4,
    "shots_off_target": 1,
    "shots_blocked": 3,
    "corners": 6,
    "corners_taken": 6,
    "corners_conceded": 6,
    "fouls": 27,
    "fouls_won": 12,
    "yellow_cards": 2,
    "possession": 48.2,
    "passes": 329,
    "passes_accurate": 251,
    "offsides": 3,
    "tackles_won": 13,
    "tackles": 18,
    "saves": 3,
    "clearances": 23,
    "big_chances_missed": 1
  }
}