{
  "slug": "saison-2025-2026-jupiler-pro-league-33-kaa-gent-vs-stvv",
  "date": "2026-04-19",
  "round": 33,
  "round_name": "Journée 33",
  "status": "FullTime",
  "referee": "Jasper Vergoote",
  "attendance": null,
  "home_team": "KAA Gent",
  "away_team": "STVV",
  "home_score": 0,
  "away_score": 0,
  "home_formation": "3412",
  "away_formation": "4231",
  "home": {
    "shots": 13,
    "shots_on_target": 2,
    "shots_off_target": 6,
    "shots_blocked": 5,
    "corners": 6,
    "corners_taken": 6,
    "corners_conceded": 5,
    "fouls": 8,
    "fouls_won": 12,
    "possession": 49.5,
    "passes": 408,
    "passes_accurate": 324,
    "offsides": 2,
    "tackles_won": 6,
    "tackles": 11,
    "saves": 3,
    "clearances": 29
  },
  "away": {
    "shots": 12,
    "shots_on_target": 3,
    "shots_off_target": 3,
    "shots_blocked": 6,
    "corners": 5,
    "corners_taken": 5,
    "corners_conceded": 6,
    "fouls": 14,
    "fouls_won": 8,
    "yellow_cards": 1,
    "possession": 50.5,
    "passes": 427,
    "passes_accurate": 330,
    "tackles_won": 6,
    "tackles": 9,
    "saves": 2,
    "clearances": 28,
    "big_chances_missed": 4
  }
}