{
  "slug": "saison-2025-2026-jupiler-pro-league-34-oh-leuven-vs-kvc-westerlo",
  "date": "2026-04-21",
  "round": 34,
  "round_name": "Journée 34",
  "status": "FullTime",
  "referee": "Kevin van Damme",
  "attendance": null,
  "home_team": "OH Leuven",
  "away_team": "KVC Westerlo",
  "home_score": 0,
  "away_score": 2,
  "home_formation": "343",
  "away_formation": "4231",
  "home": {
    "shots": 12,
    "shots_on_target": 5,
    "shots_off_target": 6,
    "shots_blocked": 1,
    "corners": 8,
    "corners_taken": 8,
    "corners_conceded": 4,
    "fouls": 10,
    "fouls_won": 4,
    "yellow_cards": 1,
    "possession": 49.2,
    "passes": 410,
    "passes_accurate": 335,
    "offsides": 8,
    "tackles_won": 9,
    "tackles": 19,
    "saves": 6,
    "clearances": 17,
    "big_chances_missed": 2
  },
  "away": {
    "shots": 16,
    "shots_on_target": 8,
    "shots_off_target": 2,
    "shots_blocked": 6,
    "corners": 4,
    "corners_taken": 4,
    "corners_conceded": 8,
    "fouls": 5,
    "fouls_won": 10,
    "possession": 50.8,
    "passes": 436,
    "passes_accurate": 348,
    "offsides": 1,
    "tackles_won": 10,
    "tackles": 16,
    "saves": 4,
    "clearances": 15,
    "big_chances_missed": 1,
    "goals": 2,
    "assists": 1
  }
}