{
  "match_id": "l1_championship_match_73319",
  "season": 2025,
  "date": "2026-02-22",
  "round": 23,
  "status": "full_time",
  "referee": "Jérémie PIGNARD",
  "attendance": 23341,
  "stadium": "STADE DE LA BEAUJOIRE-LOUIS FONTENEAU",
  "home_team": "FC Nantes",
  "away_team": "Havre AC",
  "home_score": 2,
  "away_score": 0,
  "home_formation": "352",
  "away_formation": "433",
  "home_possession": 36,
  "away_possession": 64,
  "home_shots": 9,
  "away_shots": 6,
  "home_shots_on_target": 2,
  "away_shots_on_target": 1,
  "home_shots_off_target": 2,
  "away_shots_off_target": 3,
  "home_shots_blocked": 5,
  "away_shots_blocked": 2,
  "home_corners": 5,
  "away_corners": 6,
  "home_fouls": 17,
  "away_fouls": 13,
  "home_yellow": 4,
  "away_yellow": 3,
  "home_red": null,
  "away_red": null,
  "home_xg": 1.262,
  "away_xg": 0.699,
  "home_offsides": null,
  "away_offsides": 4,
  "home_passes": 207,
  "away_passes": 526,
  "home_passes_accurate": 132,
  "away_passes_accurate": 445,
  "home_tackles": 24,
  "away_tackles": 13,
  "home_tackles_won": 14,
  "away_tackles_won": 7,
  "home_saves": 1,
  "away_saves": 1,
  "home_clearances": 42,
  "away_clearances": 25,
  "home_big_chances_missed": 2,
  "away_big_chances_missed": 2,
  "home_aerials_won": 18,
  "away_aerials_won": 23
}