{
  "match_id": "l1_championship_match_73340",
  "season": 2025,
  "date": "2026-03-06",
  "round": 25,
  "status": "full_time",
  "referee": "Ruddy BUQUET",
  "attendance": 46806,
  "stadium": "PARC DES PRINCES",
  "home_team": "PSG",
  "away_team": "AS Monaco",
  "home_score": 1,
  "away_score": 3,
  "home_formation": "433",
  "away_formation": "3412",
  "home_possession": 65,
  "away_possession": 35,
  "home_shots": 20,
  "away_shots": 11,
  "home_shots_on_target": 6,
  "away_shots_on_target": 6,
  "home_shots_off_target": 10,
  "away_shots_off_target": 3,
  "home_shots_blocked": 4,
  "away_shots_blocked": 2,
  "home_corners": 7,
  "away_corners": 3,
  "home_fouls": 12,
  "away_fouls": 6,
  "home_yellow": 1,
  "away_yellow": 3,
  "home_red": null,
  "away_red": null,
  "home_xg": 1.09,
  "away_xg": 1.335,
  "home_offsides": 1,
  "away_offsides": 2,
  "home_passes": 704,
  "away_passes": 269,
  "home_passes_accurate": 633,
  "away_passes_accurate": 203,
  "home_tackles": 18,
  "away_tackles": 25,
  "home_tackles_won": 15,
  "away_tackles_won": 18,
  "home_saves": 3,
  "away_saves": 5,
  "home_clearances": 16,
  "away_clearances": 19,
  "home_big_chances_missed": 2,
  "away_big_chances_missed": 1,
  "home_aerials_won": 15,
  "away_aerials_won": 2
}